esdap/__init__.py
esdap/helpers/__init__.py
esdap/helpers/parsers.py
esdap/processing/__init__.py
esdap/processing/compute_features.py
esdap/processing/compute_features_EEG_CHBMIT.py
esdap/processing/compute_features_EEG_neonates.py
esdap/processing/data_loading.py
esdap/processing/data_preparation.py
esdap/training/__init__.py
esdap/training/sklearn_models.py
esdap/training/tensorflow_models.py
esdap/training/train.py
esdap/training/train_sklearn.py
esdap/training/train_tensorflow.py
esdap/training/helpers/__init__.py
esdap/training/helpers/clr_callback.py
esdap/training/helpers/decay_callback.py
esdap/training/helpers/learningratefinder.py
esdap/training/helpers/metrics.py
esdap/training/helpers/metrics_callback.py
esdap/training/helpers/oclr_callback.py
esdap/training/helpers/tests.py
esdap/training/helpers/utils.py
esdap/training/models/__init__.py
esdap/training/models/cnn.py
esdap/training/models/fcn.py
esdap/training/models/lstm.py
esdap/training/models/utils.py
esdap/training/preprocessing/__init__.py
esdap/training/preprocessing/data_loader.py
esdap/training/preprocessing/data_preparation.py
esdap/training/preprocessing/preprocessing.py
esdap-1.0.3.data/scripts/run_compute_features.sh
esdap-1.0.3.dist-info/LICENSE
esdap-1.0.3.dist-info/METADATA
esdap-1.0.3.dist-info/WHEEL
esdap-1.0.3.dist-info/top_level.txt
esdap-1.0.3.dist-info/RECORD
