Metadata-Version: 2.1
Name: esdap
Version: 1.0.3
Summary: Epileptic Seizure Detection and Prediction from EEG data
Home-page: https://github.com/idupanloup/ESDaP
Author: Isabelle Dupanloup
Author-email: isabelle.dupanloup@sib.swiss
License: GNU General Public License v3.0
Platform: UNKNOWN
Classifier: License :: OSI Approved :: GNU General Public License v3 (GPLv3)
Classifier: Programming Language :: Python :: 3.7
Requires-Dist: joblib
Requires-Dist: matplotlib
Requires-Dist: mlflow
Requires-Dist: mne
Requires-Dist: numba
Requires-Dist: numpy
Requires-Dist: pandas
Requires-Dist: pywavelets
Requires-Dist: scikit-learn
Requires-Dist: scipy
Requires-Dist: seaborn
Requires-Dist: tensorflow
Requires-Dist: xgboost
